Workbook

Sheet Construction Accounting
E2: info@vegahomes.lk | H2: CONSTRUCTION ACCOUNTING
E3: www.vegahomes.lk
E4: No 494, Puttalam Road, Kurunegala
E5: +9471 274 1577, +947777 20 888
B9: Project Information | K9: Income | L9: Actual | M9: Budget | N9: Variances
B10: Project Name | D10: Commercial Office Building | K10: Contract Amount | L10: 35000000 | M10: 30000000 | N10: =L10-M10 -> 5000000
B11: Project ID | D11: VH-001 | K11: Change Orders | L11: 2500000 | M11: 1000000 | N11: =L11-M11 -> 1500000
B12: Project Manager | K12: Progress Payments | L12: 26000000 | M12: 3500000 | N12: =L12-M12 -> 22500000
B13: Project Start Date | K13: Retainage Released | L13: 1000000 | M13: 280000 | N13: =L13-M13 -> 720000
B14: Project End Date | N14: =L14-M14 -> 0
N15: =L15-M15 -> 0
B16: Total Actual Income | E16: Total Actual Expenses | H16: Net Income | N16: =L16-M16 -> 0
N17: =L17-M17 -> 0
B18: =Accounts!D262 -> 6250000 | E18: =Accounts!N262 -> 5194547 | H18: =B18-E18 -> 1055453 | N18: =L18-M18 -> 0
K19: Total Income | L19: =SUM(L10:L18) -> 64500000 | M19: =SUM(M10:M18) -> 34780000 | N19: =L19-M19 -> 29720000
B21: INCOME | K21: Expenses | L21: Actual | M21: Budget | N21: Variances
K22: Direct Costs
C23: Actual | D23: =L19 -> 64500000 | K23: Labor | L23: =GETPIVOTDATA("Total",Sheet1!$B$15,"Category","Labour") -> 497300 | M23: 48000 | N23: =L23-M23 -> 449300
C24: Budget | D24: =M19 -> 34780000 | K24: Materials | L24: =GETPIVOTDATA("Total",Sheet1!$B$15,"Category","Material") -> 989735 | M24: 32000 | N24: =L24-M24 -> 957735
K25: Equipment | L25: =GETPIVOTDATA("Total",Sheet1!$B$15,"Category","Machinery") -> 26156 | M25: 14000 | N25: =L25-M25 -> 12156
K26: Subcontractor Costs | L26: =GETPIVOTDATA("Total",Sheet1!$B$15,"Category","Sub Contractor") -> 106080 | M26: 18000 | N26: =L26-M26 -> 88080
K27: Other Direct Costs | L27: =GETPIVOTDATA("Total",Sheet1!$B$15,"Category","Other") -> 3366026 | M27: 6000 | N27: =L27-M27 -> 3360026
N28: =L28-M28 -> 0
N29: =L29-M29 -> 0
N30: =L30-M30 -> 0
B31: EXPENSES | K31: Indirect Costs
K32: Overhead | L32: 10000 | M32: 9000 | N32: =L32-M32 -> 1000
K33: Administrative Expenses | L33: 8000 | M33: 7500 | N33: =L33-M33 -> 500
K34: Insurance | L34: 3000 | M34: 3200 | N34: =L34-M34 -> -200
C35: Actual | D35: =L39 -> 5008297 | K35: Permits and Fees | L35: 2000 | M35: 1800 | N35: =L35-M35 -> 200
C36: Budget | D36: =M39 -> 139500 | N36: =L36-M36 -> 0
N37: =L37-M37 -> 0
N38: =L38-M38 -> 0
K39: Total Expenses | L39: =SUM(L23:L38) -> 5008297 | M39: =SUM(M23:M38) -> 139500 | N39: =SUM(N23:N38) -> 4868797

Sheet Sheet1
B15: Sum of Total | C15: Column Labels
B16: Row Labels | C16: Labour | D16: Machinery | E16: Material | F16: Sub Contractor | G16: Transport | H16: Other | I16: Grand Total
B17: 3/4" Metal Cube 01 | E17: 28500 | H17: 8500 | I17: 37000
B18: 6"x9" Struips | H18: 1190 | I18: 1190
B19: A.C.K Colour House | H19: 21450 | I19: 21450
B20: A.K.Hardware | H20: 4500 | I20: 4500
B21: Ajantha(Mason)/Advance | C21: 305800 | H21: 900778 | I21: 1206578
B22: Amila(Electrical)/Advance | C22: 61000 | I22: 61000
B23: Anthony's Hw | H23: 90230 | I23: 90230
B24: Binding 2Kg | H24: 800 | I24: 800
B25: Bricks = 3000Nr | H25: 99000 | I25: 99000
B26: Cainz Hw | E26: 2150 | H26: 181651 | I26: 183801
B27: Card Board | H27: 1500 | I27: 1500
B28: Cement | E28: 10780 | H28: 75300 | I28: 86080
B29: Cement Bag 06 Nr | E29: 12600 | I29: 12600
B30: Central Hw | E30: 43580 | I30: 43580
B31: Chamidu Timbers | E31: 6880 | H31: 2250 | I31: 9130
B32: Chathuranga Hw | E32: 4510 | H32: 27240 | I32: 31750
B33: Chuti Mahaththaya | F33: 17500 | H33: 50000 | I33: 67500
B34: Dewmith Construction | F34: 34500 | I34: 34500
B35: Electrical Items | H35: 1710 | I35: 1710
B36: Excavator | D36: 13500 | I36: 13500
B37: Finex Engineering | E37: 5750 | H37: 71542 | I37: 77292
B38: Foods -Mr.Nazir | F38: 2520 | I38: 2520
B39: Hardware Item | H39: 650 | I39: 650
B40: Jagath(Mason)/Salary | H40: 23200 | I40: 23200
B41: Jagath(Mason)/Salary | C41: 29000 | I41: 29000
B42: Jagath(Mason)/Salary (Slab Repairing) | C42: 5800 | I42: 5800
B43: Jayalanka Hw | H43: 10250 | I43: 10250
B44: Jenerator | H44: 10800 | I44: 10800
B45: K.S.De Silva and Son | H45: 4330 | I45: 4330
B46: Lanka Tiles | H46: 71218 | I46: 71218
B47: Linko Construction | D47: 12656 | H47: 100000 | I47: 112656
B48: Lion Plywood | E48: 38400 | I48: 38400
B49: M City Hw | E49: 1000 | I49: 1000
B50: M.M Hardware | H50: 1150 | I50: 1150
B51: Mahagalkadawala Hw | E51: 286005 | H51: 90972 | I51: 376977
B52: Manjula(Welder)/Advance | H52: 15000 | I52: 15000
B53: Modern Hardware | E53: 3880 | I53: 3880
B54: Mr.Mahiti | G54: 5000 | I54: 5000
B55: Mr.Nazir | F55: 44000 | I55: 44000
B56: Mr.Nazir (Advance Payment) | F56: 1000 | I56: 1000
B57: Mr.Nazir- Foods | F57: 1560 | I57: 1560
B58: Mr.Nazir-Brick Wall Demolish | F58: 5000 | I58: 5000
B59: Multi Hw | E59: 700 | I59: 700
B60: Neel(Tree Cutter) | H60: 7000 | I60: 7000
B61: Nilu(Mason)/Advance | C61: 1000 | H61: 5000 | I61: 6000
B62: Nilu(Mason)/Salary | C62: 85700 | H62: 20900 | I62: 106600
B63: Pearl waterproofing solution | H63: 75000 | I63: 75000
B64: Polythene | H64: 1200 | I64: 1200
B65: Priyantha(u/sk)/Advance | C65: 1000 | I65: 1000
B66: Ravi(Painter)/Advance | H66: 29000 | I66: 29000
B67: Removing Glass Roof | C67: 8000 | I67: 8000
B68: Ruwan(Tiler)/Advance | H68: 118300 | I68: 118300
B69: S.M.Metals | H69: 3600 | I69: 3600
B70: S.N.S.Construction | H70: 2000 | I70: 2000
B71: Sand Cube 01 | E71: 45000 | H71: 69500 | I71: 114500
B72: Sand Cube 02 | H72: 90000 | I72: 90000
B73: SF Putty | H73: 5500 | I73: 5500
B74: Sika/Waterproofing | H74: 415065 | I74: 415065
B75: Site Visit | G75: 2500 | I75: 2500
B76: Site Visit | G76: 29950 | I76: 29950
B77: St Anthonys' Hardware | E77: 500000 | I77: 500000
B78: Star Hw | H78: 130625 | I78: 130625
B79: Store | H79: 20000 | I79: 20000
B80: Track Repairing | H80: 75000 | I80: 75000
B81: Vega (Tools Rent) | H81: 400475 | I81: 400475
B82: Welagedara Hw | H82: 32650 | I82: 32650
B83: Transport | G83: 171800 | I83: 171800
B84: Grand Total | C84: 497300 | D84: 26156 | E84: 989735 | F84: 106080 | G84: 209250 | H84: 3366026 | I84: 5194547
B88: TOTAL RECEIVED | C88: =Table1[[#Totals],[Cumulative]] -> 6250000
B90: TOTAL EXPENSES | C90: =GETPIVOTDATA("Total",$B$15) -> 5194547
B92: OUTSTANDING PAYMENTS | C92: =Table1[[#Totals],[Outstanding Payments]] -> 5194547
B94: 70% OF TOTAL RECEIVED | C94: =C88*0.7 -> 4375000
B96: BALANCE | C96: =C94-C92-C90 -> -6014094

Sheet Accounts
A1: Mr. Lalith Suranga (Millawa/New Works) | O1: =SUM(O6:O261) -> 500000 | P1: =SUM(P6:P261) -> 173500 | Q1: =SUM(Q6:Q261) -> 0 | R1: =SUM(R6:R261) -> 0 | S1: =SUM(S6:S261) -> 57500 | T1: =SUM(T6:T261) -> 0 | U1: =SUM(U6:U261) -> 13500 | V1: =SUM(V6:V261) -> 5000 | ... Z1: =SUM(Z6:Z261) -> 0
A3: INCOME BALANCE STATEMENT
A5: Date | B5: Payment No | C5: Amount | D5: Cumulative | E5: Remarks | F5: Date2 | G5: Entry No | H5: Description | I5: Category | J5: Memo | K5: Stage | L5: BOQ Item | M5: Total | N5: Cumulative2 | O5: Outstanding Payments | P5: Transport | Q5: Labour / Sub Contractor | R5: Site Visit | S5: Machinery | T5: Minor Material | U5: Major Material | V5: Service Charge | W5: Utility Bills | X5: Food & Beverages | Y5: Fuel | Z5: Others
A6: 45107 | B6: 1 | C6: 500000 | D6: 500000 | E6: Cash | F6: 45091 | G6: 1 | H6: Site Visit | I6: Transport | J6: 06/1103 | K6: Stage-01 | L6: Tile Works | M6: 5000 | N6: =M6 -> 5000 | P6: 5000
A7: 45134 | B7: 1 | C7: 500000 | D7: =D6+C7 -> 1000000 | E7: Bank | F7: 45091 | G7: 2 | H7: Mr.Mahiti | I7: Transport | J7: 06/1104 | K7: Stage-02 | L7: Plastering Works | M7: 5000 | N7: =M7+N6 -> 10000 | V7: 5000
A8: 45204 | B8: 1 | C8: 500000 | D8: =D7+C8 -> 1500000 | E8: Online | F8: 45105 | G8: 3 | H8: Mahagalkadawala Hw | I8: Material | J8: 06/1118 | K8: Stage-03 | L8: Painting Works | M8: 8400 | N8: =M8+N7 -> 18400
A9: 45211 | B9: 1 | C9: 500000 | D9: =D8+C9 -> 2000000 | E9: Bank | F9: 45104 | G9: 4 | H9: Ajantha(Mason)/Advance | I9: Labour | J9: 06/1120 | K9: Stage-04 | L9: Aluminium Works | M9: 5000 | N9: =M9+N8 -> 23400
A10: 45231 | B10: 1 | C10: 1500000 | D10: =D9+C10 -> 3500000 | E10: Online | F10: 45103 | G10: 5 | H10: Site Visit | I10: Transport | J10: 06/1126 | K10: Stage-05 | L10: Timber Works | M10: 2500 | N10: =M10+N9 -> 25900 | P10: 2500
A11: 45311 | B11: 1 | C11: 1000000 | D11: =D10+C11 -> 4500000 | E11: Bank | F11: 45106 | G11: 6 | H11: Transport | I11: Transport | J11: 06/1129 | K11: Stage-06 | L11: Steel Works | M11: 5000 | N11: =M11+N10 -> 30900 | P11: 2500
A12: 45350 | B12: 1 | C12: 700000 | D12: =D11+C12 -> 5200000 | E12: Bank | F12: 45104 | G12: 7 | H12: Transport | I12: Transport | J12: 06/1130 | L12: Waterproofing | M12: 5000 | N12: =M12+N11 -> 35900 | P12: 5000
A13: 45362 | B13: 1 | C13: 300000 | D13: =D12+C13 -> 5500000 | E13: Online | F13: 45108 | G13: 8 | H13: Ajantha(Mason)/Advance | I13: Labour | J13: 06/1141 | L13: Roofing | M13: 16300 | N13: =M13+N12 -> 52200
A14: 45389 | B14: 1 | C14: 250000 | D14: =D13+C14 -> 5750000 | E14: Bank | F14: 45108 | G14: 9 | H14: Removing Glass Roof | I14: Labour | J14: 07/1146 | L14: Electrical Works | M14: 8000 | N14: =M14+N13 -> 60200
A15: 45392 | B15: 1 | C15: 500000 | D15: =D14+C15 -> 6250000 | E15: Bank | F15: 45111 | G15: 10 | H15: Transport | I15: Transport | J15: 07/1146 | L15: Masonry Works | M15: 5100 | N15: =M15+N14 -> 65300 | P15: 5100
B16: 1 | F16: 45111 | G16: 11 | H16: Foods -Mr.Nazir | I16: Sub Contractor | J16: 07/1147 | L16: Plumbing Works | M16: 2520 | N16: =M16+N15 -> 67820 | W16: 2520
B17: 1 | F17: 45111 | G17: 12 | H17: Mr.Nazir (Advance Payment) | I17: Sub Contractor | J17: 07/1148 | L17: Rain Gutters | M17: 1000 | N17: =M17+N16 -> 68820
B18: 1 | F18: 45111 | G18: 13 | H18: Transport | I18: Transport | J18: 07/1149 | M18: 5000 | N18: =M18+N17 -> 73820 | P18: 5000
B19: 1 | F19: 45111 | G19: 14 | H19: Chathuranga Hw | I19: Material | J19: 07/1151 | M19: 3160 | N19: =M19+N18 -> 76980
B20: 1 | F20: 45111 | G20: 15 | H20: Multi Hw | I20: Material | J20: 07/1152 | M20: 700 | N20: =M20+N19 -> 77680
B21: 1 | F21: 45112 | G21: 16 | H21: Mr.Nazir-Brick Wall Demolish | I21: Sub Contractor | J21: 07/1154 | M21: 5000 | N21: =M21+N20 -> 82680
B22: 1 | F22: 45112 | G22: 17 | H22: Mr.Nazir | I22: Sub Contractor | J22: 07/1155 | M22: 44000 | N22: =M22+N21 -> 126680
B23: 1 | F23: 45112 | G23: 18 | H23: Transport | I23: Transport | J23: 07/1156 | M23: 6000 | N23: =M23+N22 -> 132680 | P23: 6000
B24: 1 | F24: 45112 | G24: 19 | H24: Mr.Nazir- Foods | I24: Sub Contractor | J24: 07/1157 | M24: 1560 | N24: =M24+N23 -> 134240 | W24: 1560
B25: 1 | F25: 45113 | G25: 20 | H25: Site Visit | I25: Transport | J25: 07/1159 | M25: 2700 | N25: =M25+N24 -> 136940 | P25: 2700
B26: 1 | F26: 45115 | G26: 21 | H26: Nilu(Mason)/Salary | I26: Labour | J26: 07/1172 | M26: 17500 | N26: =M26+N25 -> 154440
B27: 1 | F27: 45119 | G27: 22 | H27: Cement | I27: Material | J27: 07/1183 | M27: 4400 | N27: =M27+N26 -> 158840
B28: 1 | F28: 45119 | G28: 23 | H28: Transport | I28: Transport | J28: 07/1184 | M28: 2500 | N28: =M28+N27 -> 161340 | P28: 2500
B29: 1 | F29: 45120 | G29: 24 | H29: Nilu(Mason)/Advance | I29: Labour | J29: 07/1191 | M29: 1000 | N29: =M29+N28 -> 162340
B30: 1 | F30: 45122 | G30: 25 | H30: Nilu(Mason)/Salary | I30: Labour | J30: 07/1193 | M30: 16400 | N30: =M30+N29 -> 178740
B31: 1 | F31: 45125 | G31: 26 | H31: Site Visit | I31: Transport | J31: 07/1204 | M31: 2500 | N31: =M31+N30 -> 181240 | P31: 2500
B32: 1 | F32: 45127 | G32: 27 | H32: Mahagalkadawala Hw | I32: Material | J32: 07/1211 | M32: 56580 | N32: =M32+N31 -> 237820
B33: 1 | F33: 45127 | G33: 28 | H33: Site Visit | I33: Transport | J33: 07/1215 | M33: 6750 | N33: =M33+N32 -> 244570 | P33: 6750
B34: 1 | F34: 45128 | G34: 29 | H34: Priyantha(u/sk)/Advance | I34: Labour | J34: 07/1216 | M34: 1000 | N34: =M34+N33 -> 245570
B35: 1 | F35: 45128 | G35: 30 | H35: Site Visit | I35: Transport | J35: 07/1217 | M35: 3000 | N35: =M35+N34 -> 248570 | P35: 3000
B36: 1 | F36: 45129 | G36: 31 | H36: Nilu(Mason)/Salary | I36: Labour | J36: 07/1218 | M36: 25100 | N36: =M36+N35 -> 273670
B37: 1 | F37: 45131 | G37: 32 | H37: Cement Bag 06 Nr | I37: Material | J37: 07/1227 | M37: 12600 | N37: =M37+N36 -> 286270
B38: 1 | F38: 45131 | G38: 33 | H38: Sand Cube 01 | I38: Material | J38: 07/1228 | M38: 15000 | N38: =M38+N37 -> 301270
B39: 1 | F39: 45131 | G39: 34 | H39: 3/4" Metal Cube 01 | I39: Material | J39: 07/1229 | M39: 9500 | N39: =M39+N38 -> 310770
B40: 1 | F40: 45134 | G40: 35 | H40: Ajantha(Mason)/Advance | I40: Labour | J40: 07/1237 | M40: 2000 | N40: =M40+N39 -> 312770
B41: 1 | F41: 45136 | G41: 36 | H41: Ajantha(Mason)/Advance | I41: Labour | J41: 07/1241 | M41: 41600 | N41: =M41+N40 -> 354370
B42: 1 | F42: 45133 | G42: 37 | H42: Linko Construction | I42: Machinery | J42: 07/1242 | M42: 1000 | N42: =M42+N41 -> 355370
B43: 1 | F43: 45134 | G43: 38 | H43: Site Visit | I43: Transport | J43: 07/1247 | M43: 2500 | N43: =M43+N42 -> 357870 | P43: 2500
B44: 1 | F44: 45135 | G44: 39 | H44: Site Visit | I44: Transport | J44: 07/1248 | M44: 2400 | N44: =M44+N43 -> 360270 | P44: 2400
B45: 1 | F45: 45136 | G45: 40 | H45: Site Visit | I45: Transport | J45: 07/1249 | M45: 2400 | N45: =M45+N44 -> 362670 | P45: 2400
B46: 1 | F46: 45143 | G46: 41 | H46: Ajantha(Mason)/Advance | I46: Labour | J46: 07/1252 | M46: 23300 | N46: =M46+N45 -> 385970
B47: 1 | F47: 45143 | G47: 42 | H47: Chuti Mahaththaya | I47: Sub Contractor | J47: 07/1254 | M47: 17500 | N47: =M47+N46 -> 403470 | S47: 17500
B48: 1 | F48: 45150 | G48: 43 | H48: Ajantha(Mason)/Advance | I48: Labour | J48: 08/1285 | M48: 14000 | N48: =M48+N47 -> 417470
B49: 1 | F49: 45154 | G49: 44 | H49: Mahagalkadawala Hw | I49: Material | J49: 08/1297 | M49: 28305 | N49: =M49+N48 -> 445775
B50: 1 | F50: 45155 | G50: 45 | H50: Ajantha(Mason)/Advance | I50: Labour | J50: 08/1298 | M50: 1000 | N50: =M50+N49 -> 446775
B51: 1 | F51: 45157 | G51: 46 | H51: Ajantha(Mason)/Advance | I51: Labour | J51: 08/1306 | M51: 28000 | N51: =M51+N50 -> 474775
B52: 1 | F52: 45156 | G52: 47 | H52: Mahagalkadawala Hw | I52: Material | J52: 08/1307 | M52: 10000 | N52: =M52+N51 -> 484775
B53: 1 | F53: 45156 | G53: 48 | H53: Cainz Hw | I53: Material | J53: 08/1308 | M53: 2150 | N53: =M53+N52 -> 486925
B54: 1 | F54: 45159 | G54: 49 | H54: Chathuranga Hw | I54: Material | J54: 08/1329 | M54: 1350 | N54: =M54+N53 -> 488275
B55: 1 | F55: 45164 | G55: 50 | H55: Ajantha(Mason)/Advance | I55: Labour | J55: 08/1337 | M55: 17400 | N55: =M55+N54 -> 505675
B56: 1 | F56: 45166 | G56: 51 | H56: Ajantha(Mason)/Advance | I56: Labour | J56: 08/1355 | M56: 5000 | N56: =M56+N55 -> 510675
B57: 1 | F57: 45166 | G57: 52 | H57: Dewmith Construction | I57: Sub Contractor | J57: 08/1356 | M57: 34500 | N57: =M57+N56 -> 545175
B58: 1 | F58: 45171 | G58: 53 | H58: Ajantha(Mason)/Advance | I58: Labour | J58: 09/1364 | M58: 11600 | N58: =M58+N57 -> 556775
B59: 1 | F59: 45174 | G59: 54 | H59: Central Hw | I59: Material | J59: 09/1375 | M59: 10100 | N59: =M59+N58 -> 566875
B60: 1 | F60: 45175 | G60: 55 | H60: Transport | I60: Transport | J60: 09/1375 | M60: 750 | N60: =M60+N59 -> 567625 | P60: 750
B61: 1 | F61: 45173 | G61: 56 | H61: Mahagalkadawala Hw | I61: Material | J61: 09/1381 | M61: 22015 | N61: =M61+N60 -> 589640
B62: 1 | F62: 45176 | G62: 57 | H62: Central Hw | I62: Material | J62: 09/1386 | M62: 33480 | N62: =M62+N61 -> 623120 | AX62: =AW62+AX61 -> 0 | AY62: =AX62+AY61 -> 0 | AZ62: =AY62+AZ61 -> 0 | BA62: =AZ62+BA61 -> 0 | BB62: =BA62+BB61 -> 0
B63: 1 | F63: 45177 | G63: 58 | H63: Excavator | I63: Machinery | J63: 09/1387 | M63: 13500 | N63: =M63+N62 -> 636620 | U63: 13500 | AX63: =AW63+AX62 -> 0 | AY63: =AX63+AY62 -> 0 | AZ63: =AY63+AZ62 -> 0 | BA63: =AZ63+BA62 -> 0 | BB63: =BA63+BB62 -> 0
B64: 1 | F64: 45177 | G64: 59 | H64: Sand Cube 01 | I64: Material | J64: 09/1389 | M64: 15000 | N64: =M64+N63 -> 651620
B65: 1 | F65: 45177 | G65: 60 | H65: 3/4" Metal Cube 01 | I65: Material | J65: 09/1390 | M65: 9500 | N65: =M65+N64 -> 661120
B66: 1 | F66: 45178 | G66: 61 | H66: M City Hw | I66: Material | J66: 09/1405 | M66: 1000 | N66: =M66+N65 -> 662120
B67: 1 | F67: 45178 | G67: 62 | H67: Chamidu Timbers | I67: Material | J67: 09/1408 | M67: 6880 | N67: =M67+N66 -> 669000
B68: 1 | F68: 45128 | G68: 63 | H68: Site Visit | I68: Transport | J68: 09/1431 | M68: 2700 | N68: =M68+N67 -> 671700 | P68: 2700
B69: 1 | F69: 45131 | G69: 64 | H69: St Anthonys' Hardware | I69: Material | J69: 09/1432 | M69: 500000 | N69: =M69+N68 -> 1171700 | O69: 500000 | P69: 2250
B70: 1 | F70: 45133 | G70: 65 | H70: Transport | I70: Transport | J70: 09/1433 | M70: 2250 | N70: =M70+N69 -> 1173950 | P70: 2250
B71: 1 | F71: 45170 | G71: 66 | H71: Transport | I71: Transport | J71: 09/1434 | M71: 2250 | N71: =M71+N70 -> 1176200 | P71: 2250
B72: 1 | F72: 45173 | G72: 67 | H72: Transport | I72: Transport | J72: 09/1435 | M72: 3150 | N72: =M72+N71 -> 1179350 | P72: 3150
B73: 1 | F73: 45176 | G73: 68 | H73: Transport | I73: Transport | J73: 09/1436 | M73: 2400 | N73: =M73+N72 -> 1181750 | P73: 2400
B74: 1 | F74: 45177 | G74: 69 | H74: Transport | I74: Transport | J74: 09/1437 | M74: 2400 | N74: =M74+N73 -> 1184150 | P74: 2400
B75: 1 | F75: 45178 | G75: 70 | H75: Ajantha(Mason)/Advance | I75: Labour | J75: 09/1445 | M75: 29800 | N75: =M75+N74 -> 1213950
B76: 1 | F76: 45185 | G76: 71 | H76: Ajantha(Mason)/Advance | I76: Labour | J76: 09/1450 | M76: 5800 | N76: =M76+N75 -> 1219750
B77: 1 | F77: 45185 | G77: 72 | H77: Jagath(Mason)/Salary (Slab Repairing) | I77: Labour | J77: 09/1457 | M77: 5800 | N77: =M77+N76 -> 1225550
B78: 1 | F78: 45185 | G78: 73 | H78: Ajantha(Mason)/Advance | I78: Labour | J78: 09/1452 | M78: 6600 | N78: =M78+N77 -> 1232150
B79: 1 | F79: 45183 | G79: 74 | H79: Ajantha(Mason)/Advance | I79: Labour | J79: 09/1457 | M79: 5000 | N79: =M79+N78 -> 1237150
B80: 1 | F80: 45182 | G80: 75 | H80: Mahagalkadawala Hw | I80: Material | J80: 09/1460 | M80: 18680 | N80: =M80+N79 -> 1255830
B81: 1 | F81: 45186 | G81: 76 | H81: Ajantha(Mason)/Advance | I81: Labour | J81: 09/1503 | M81: 14500 | N81: =M81+N80 -> 1270330
B82: 1 | F82: 45199 | G82: 77 | H82: Ajantha(Mason)/Advance | I82: Labour | J82: 09/1527 | M82: 17400 | N82: =M82+N81 -> 1287730
B83: 1 | F83: 45198 | G83: 78 | H83: Modern Hardware | I83: Material | J83: 09/1533 | M83: 3880 | N83: =M83+N82 -> 1291610
B84: 1 | F84: 45199 | G84: 79 | H84: Linko Construction | I84: Machinery | J84: 09/1539 | M84: 8056 | N84: =M84+N83 -> 1299666
B85: 1 | F85: 45199 | G85: 80 | H85: Linko Construction | I85: Machinery | J85: 09/1540 | M85: 3600 | N85: =M85+N84 -> 1303266
B86: 1 | F86: 45203 | G86: 81 | H86: Ajantha(Mason)/Advance | I86: Labour | J86: 10/1546 | M86: 1000 | N86: =M86+N85 -> 1304266
... B91: 1 | F91: 45206 | G91: 86 | H91: Nilu(Mason)/Salary | I91: Labour | J91: 10/1566 | M91: 15100 | N91: =M91+N90 -> 1359546
B92: 1 | F92: 45208 | G92: 87 | H92: Transport | I92: Transport | J92: 10/1569 | M92: 2250 | N92: =M92+N91 -> 1361796 | P92: 2250
B93: 1 | F93: 45213 | G93: 88 | H93: Nilu(Mason)/Salary | I93: Labour | J93: 10/1584 | M93: 5800 | N93: =M93+N92 -> 1367596
B94: 1 | F94: 45213 | G94: 89 | H94: Jagath(Mason)/Salary | I94: Labour | J94: 10/1586 | M94: 11600 | N94: =M94+N93 -> 1379196
B95: 1 | F95: 45207 | G95: 90 | H95: Jagath(Mason)/Salary | I95: Labour | J95: 10/1587 | M95: 17400 | N95: =M95+N94 -> 1396596
B96: 1 | F96: 45213 | G96: 91 | H96: Ajantha(Mason)/Advance | I96: Labour | J96: 10/1588 | M96: 3500 | N96: =M96+N95 -> 1400096
B97: 1 | F97: 45213 | G97: 92 | H97: Ajantha(Mason)/Advance | I97: Labour | J97: 10/1589 | M97: 29000 | N97: =M97+N96 -> 1429096
B98: 1 | F98: 45212 | G98: 93 | H98: Transport | I98: Transport | J98: 10/1590 | M98: 2500 | N98: =M98+N97 -> 1431596 | P98: 2500
B99: 1 | F99: 45212 | G99: 94 | H99: Lion Plywood | I99: Material | J99: 10/1594 | M99: 38400 | N99: =M99+N98 -> 1469996
B100: 1 | F100: 45213 | G100: 95 | H100: Mahagalkadawala Hw | I100: Material | J100: 10/1595 | M100: 142025 | N100: =M100+N99 -> 1612021
B101: 1 | F101: 45213 | G101: 96 | H101: Transport | I101: Transport | J101: 10/1596 | M101: 2000 | N101: =M101+N100 -> 1614021 | P101: 2000
B102: 1 | F102: 45216 | G102: 97 | H102: Finex Engineering | I102: Material | J102: 10/1601 | M102: 5750 | N102: =M102+N101 -> 1619771
B103: 1 | F103: 45216 | G103: 98 | H103: 3/4" Metal Cube 01 | I103: Material | J103: 10/1605 | M103: 9500 | N103: =M103+N102 -> 1629271
B104: 1 | F104: 45216 | G104: 99 | H104: Sand Cube 01 | I104: Material | J104: 10/1606 | M104: 15000 | N104: =M104+N103 -> 1644271
B105: 1 | F105: 45219 | G105: 100 | H105: Jenerator | I105: Other | J105: 10/1607 | M105: 10800 | N105: =M105+N104 -> 1655071
B106: 1 | F106: 45220 | G106: 101 | H106: Nilu(Mason)/Salary | I106: Other | J106: 10/1610 | M106: 20900 | N106: =M106+N105 -> 1675971
...
